<?xml version="1.0" encoding="utf-8" ?>
<dwsync>
<file name="style.css" server="ftp.wpdev.cahnrs.wsu.edu//public_html/devsite.wpdev.cahnrs.wsu.edu/wp-content/themes/CAHNRSWP-Theme-Commodities/" local="130717046576013878" remote="130717046400000000" Dst="2" />
<file name="functions.php" server="ftp.wpdev.cahnrs.wsu.edu//public_html/devsite.wpdev.cahnrs.wsu.edu/wp-content/themes/CAHNRSWP-Theme-Commodities/" local="130716845792131045" remote="130716845400000000" Dst="2" />
<file name="sidebar.php" server="ftp.wpdev.cahnrs.wsu.edu//public_html/devsite.wpdev.cahnrs.wsu.edu/wp-content/themes/CAHNRSWP-Theme-Commodities/" local="130692979328326820" remote="130700324400000000" Dst="1" />
<file name="single-video.php" server="ftp.wpdev.cahnrs.wsu.edu//public_html/devsite.wpdev.cahnrs.wsu.edu/wp-content/themes/CAHNRSWP-Theme-Commodities/" local="130674510083706962" remote="130700324400000000" Dst="1" />
<file name="category.php" server="ftp.wpdev.cahnrs.wsu.edu//public_html/devsite.wpdev.cahnrs.wsu.edu/wp-content/themes/CAHNRSWP-Theme-Commodities/" local="130700314609413535" remote="130700324400000000" Dst="1" />
<file name="archive.php" server="ftp.wpdev.cahnrs.wsu.edu//public_html/devsite.wpdev.cahnrs.wsu.edu/wp-content/themes/CAHNRSWP-Theme-Commodities/" local="130716844170837403" remote="130716843600000000" Dst="2" />
<file name="archive-video2.php" server="ftp.wpdev.cahnrs.wsu.edu//public_html/devsite.wpdev.cahnrs.wsu.edu/wp-content/themes/CAHNRSWP-Theme-Commodities/" local="130698861588398606" remote="130698877800000000" Dst="1" />
<file name="archive-video - Copy.php" server="ftp.wpdev.cahnrs.wsu.edu//public_html/devsite.wpdev.cahnrs.wsu.edu/wp-content/themes/CAHNRSWP-Theme-Commodities/" local="130698861588228443" remote="130698877800000000" Dst="1" />
<file name="archive-publication2.php" server="ftp.wpdev.cahnrs.wsu.edu//public_html/devsite.wpdev.cahnrs.wsu.edu/wp-content/themes/CAHNRSWP-Theme-Commodities/" local="130698861588078312" remote="130698877800000000" Dst="1" />
<file name="archive-news2.php" server="ftp.wpdev.cahnrs.wsu.edu//public_html/devsite.wpdev.cahnrs.wsu.edu/wp-content/themes/CAHNRSWP-Theme-Commodities/" local="130698861588068311" remote="130698877800000000" Dst="1" />
</dwsync>